CHANGELOG.md
LICENSE
MANIFEST.in
README.rst
setup.cfg
setup.py
django_async_test/__init__.py
django_async_test/testcase.py
django_async_test.egg-info/PKG-INFO
django_async_test.egg-info/SOURCES.txt
django_async_test.egg-info/dependency_links.txt
django_async_test.egg-info/not-zip-safe
django_async_test.egg-info/requires.txt
django_async_test.egg-info/top_level.txt
django_async_test/tests/__init__.py
django_async_test/tests/test_testcase.py
django_async_test/tests/testapp/__init__.py
django_async_test/tests/testapp/models.py
django_async_test/tests/testapp/settings.py
django_async_test/tests/testapp/util.py
docs/Makefile
docs/conf.py
docs/developer.rst
docs/index.rst
docs/installation.rst
docs/usage.rst
docs/_build/doctrees/developer.doctree
docs/_build/doctrees/environment.pickle
docs/_build/doctrees/index.doctree
docs/_build/doctrees/installation.doctree
docs/_build/doctrees/usage.doctree
docs/_build/doctrees/internals/reference/django_async_test.testcase.doctree
docs/_build/doctrees/internals/reference/index.doctree
docs/_build/html/.buildinfo
docs/_build/html/developer.html
docs/_build/html/genindex.html
docs/_build/html/index.html
docs/_build/html/installation.html
docs/_build/html/objects.inv
docs/_build/html/py-modindex.html
docs/_build/html/search.html
docs/_build/html/searchindex.js
docs/_build/html/usage.html
docs/_build/html/_modules/index.html
docs/_build/html/_modules/django_async_test/testcase.html
docs/_build/html/_sources/developer.txt
docs/_build/html/_sources/index.txt
docs/_build/html/_sources/installation.txt
docs/_build/html/_sources/usage.txt
docs/_build/html/_sources/internals/reference/django_async_test.testcase.txt
docs/_build/html/_sources/internals/reference/index.txt
docs/_build/html/_static/ajax-loader.gif
docs/_build/html/_static/basic.css
docs/_build/html/_static/comment-bright.png
docs/_build/html/_static/comment-close.png
docs/_build/html/_static/comment.png
docs/_build/html/_static/doctools.js
docs/_build/html/_static/down-pressed.png
docs/_build/html/_static/down.png
docs/_build/html/_static/file.png
docs/_build/html/_static/jquery-1.11.1.js
docs/_build/html/_static/jquery.js
docs/_build/html/_static/minus.png
docs/_build/html/_static/plus.png
